notekeras/__init__.py
notekeras/backend.py
notekeras/tokenizer.py
notekeras/activations/__init__.py
notekeras/activations/core.py
notekeras/algorithm/__init__.py
notekeras/algorithm/models.py
notekeras/component/__init__.py
notekeras/component/components.py
notekeras/component/core.py
notekeras/component/resnet_bolck.py
notekeras/component/transformer.py
notekeras/component/image/__init__.py
notekeras/component/image/core.py
notekeras/component/yolo/__init__.py
notekeras/component/yolo/core.py
notekeras/component/yolo/yolo3.py
notekeras/features/__init__.py
notekeras/features/core.py
notekeras/features/example.py
notekeras/features/feature_column_def.py
notekeras/features/feature_parse.py
notekeras/features/feature_parse_keras.py
notekeras/features/parse_pandas.py
notekeras/initializers/__init__.py
notekeras/initializers/core.py
notekeras/inputs/__init__.py
notekeras/inputs/core.py
notekeras/layers/__init__.py
notekeras/layers/activations.py
notekeras/layers/attention.py
notekeras/layers/conv.py
notekeras/layers/core.py
notekeras/layers/embedding.py
notekeras/layers/extract.py
notekeras/layers/feed_forward.py
notekeras/layers/fm.py
notekeras/layers/inputs.py
notekeras/layers/masked.py
notekeras/layers/normalize.py
notekeras/layers/pooling.py
notekeras/layers/retinanet.py
notekeras/layers/wrappers.py
notekeras/layers/graph/__init__.py
notekeras/layers/graph/base.py
notekeras/layers/graph/conv.py
notekeras/layers/graph/mpnn.py
notekeras/layers/graph/pool.py
notekeras/layers/graph/utils.py
notekeras/models/__init__.py
notekeras/models/benchmarks.py
notekeras/models/bert.py
notekeras/models/inception.py
notekeras/models/loader.py
notekeras/models/resnet.py
notekeras/models/similarity.py
notekeras/models/temp.py
notekeras/models/text.py
notekeras/models/transformer.py
notekeras/models/din/__init__.py
notekeras/models/din/model.py
notekeras/models/din/train.py
notekeras/models/fm/__init__.py
notekeras/models/fm/core.py
notekeras/models/fm/model.py
funkeras-0.8.12.dist-info/METADATA
funkeras-0.8.12.dist-info/WHEEL
funkeras-0.8.12.dist-info/top_level.txt
funkeras-0.8.12.dist-info/RECORD
