Metadata-Version: 2.1
Name: funkeras
Version: 0.8.12
Summary: funkeras
Home-page: https://github.com/farfarfun/funkeras
Author: bingtao
Author-email: 1007530194@qq.com
Requires-Dist: tensorflow
Requires-Dist: numpy
Requires-Dist: scipy
Requires-Dist: opencv-python
Requires-Dist: pillow
Requires-Dist: tqdm
